leitordenotas/__init__.py
leitordenotas/models.py
leitordenotas/nota_de_corretagem_reader.py
leitordenotas/builder/__init__.py
leitordenotas/builder/builder_reader_base.py
leitordenotas/builder/clear_reader_builder.py
leitordenotas/builder/easynvest_reader_builder.py
leitordenotas/builder/inter_reader_builder.py
leitor_de_notas-0.0.1.dist-info/LICENSE
leitor_de_notas-0.0.1.dist-info/METADATA
leitor_de_notas-0.0.1.dist-info/WHEEL
leitor_de_notas-0.0.1.dist-info/top_level.txt
leitor_de_notas-0.0.1.dist-info/RECORD
